#!/usr/bin/env python3
# Author: ChengYi
# Mail: chengyi818@foxmail.cn
# created time: Fri 19 Jan 2018 12:14:29 PM CST

from A.tank import b

#print(locals())
#print(b)

# 6           0 LOAD_CONST               0 (-1)
#             3 LOAD_CONST               1 (('b',))
#             6 IMPORT_NAME              0 (A.tank)
#             9 IMPORT_FROM              1 (b)
#            12 STORE_NAME               1 (b)
#            15 POP_TOP
#            16 LOAD_CONST               2 (None)
#            19 RETURN_VALUE 
